LICENCE
MANIFEST.in
README.rst
requirements.txt
setup.py
huron/__init__.py
huron.egg-info/PKG-INFO
huron.egg-info/SOURCES.txt
huron.egg-info/dependency_links.txt
huron.egg-info/not-zip-safe
huron.egg-info/top_level.txt
huron/blog/__init__.py
huron/blog/admin.py
huron/blog/feeds.py
huron/blog/models.py
huron/blog/sitemaps.py
huron/blog/tests.py
huron/blog/urls.py
huron/blog/views.py
huron/blog/fixtures/initial_data.json
huron/blog/templates/blog/index.html
huron/blog/templates/blog/single.html
huron/contact_form/__init__.py
huron/contact_form/forms.py
huron/contact_form/models.py
huron/contact_form/tests.py
huron/contact_form/urls.py
huron/contact_form/views.py
huron/contact_form/locale/fr/LC_MESSAGES/django.po
huron/contact_form/locale/pt_BR/LC_MESSAGES/django.po
huron/contact_form/locale/ru/LC_MESSAGES/django.po
huron/contact_form/templates/contact_form/contact.html
huron/contact_form/templates/contact_form/contact_completed.html
huron/contact_form/templates/contact_form/email_subject.txt
huron/contact_form/templates/contact_form/email_template.txt
huron/menus_manager/__init__.py
huron/menus_manager/admin.py
huron/menus_manager/admin_views.py
huron/menus_manager/models.py
huron/menus_manager/tests.py
huron/menus_manager/urls.py
huron/menus_manager/views.py
huron/menus_manager/static/css/menus_manager.css
huron/menus_manager/static/js/menus_manager.js
huron/menus_manager/templates/admin/menus_manager/menu/change_form.html
huron/menus_manager/templates/admin/menus_manager/snippets/block_menu_item.html
huron/menus_manager/templates/menu/menu.html
huron/pages/__init__.py
huron/pages/admin.py
huron/pages/models.py
huron/pages/tests.py
huron/pages/urls.py
huron/pages/views.py
huron/pages/locale/fr/LC_MESSAGES/django.po
huron/pages/templates/pages/single.html
huron/settings/__init__.py
huron/settings/admin.py
huron/settings/context_processors.py
huron/settings/models.py
huron/settings/tests.py
huron/settings/views.py
huron/settings/locale/fr/LC_MESSAGES/django.po
huron/settings/templatetags/__init__.py
huron/settings/templatetags/settings_custom.py
huron/simple_medias_manager/__init__.py
