Metadata-Version: 1.0
Name: huron
Version: 0.5.4
Summary: Tools for Django websites
Home-page: https://bitbucket.org/tominardi/huron
Author: Thomas Durey
Author-email: tominardi@gmail.com
License: BSD
Platform: Linux
